Workbook

Sheet Raw_Data
A1: Product type | B1: SKU | C1: Price | D1: Availability | E1: Number of products sold | F1: Revenue generated | G1: Customer demographics | H1: Stock levels | I1: Shipping Lead time | J1: Order quantities | K1: Shipping times | L1: Shipping costs | M1: Shipping carriers | N1: Supplier name | O1: Location | P1: Production volumes | Q1: Manufacturing lead time | R1: Manufacturing costs | S1: Inspection results | T1: Defect rates | U1: Transportation modes | V1: Routes | W1: Costs
A2: haircare | B2: SKU0 | C2: 69.808006 | D2: 55 | E2: 802 | F2: 8661.9968 | G2: Non-binary | H2: 58 | I2: 7 | J2: 96 | K2: 4 | L2: 103 | M2: Carrier B | N2: Supplier 3 | O2: Mumbai | P2: 215 | Q2: 29 | R2: 46.279879 | S2: Pending | T2: 0.22641036 | U2: Road | V2: Route B | W2: 187.75208
A3: skincare | B3: SKU1 | C3: 14.843523 | D3: 95 | E3: 736 | F3: 7460.9001 | G3: Female | H3: 53 | I3: 30 | J3: 37 | K3: 2 | L3: 938 | M3: Carrier A | N3: Supplier 3 | O3: Mumbai | P3: 517 | Q3: 30 | R3: 33.616769 | S3: Pending | T3: 4.854068 | U3: Road | V3: Route B | W3: 503.06558
A4: haircare | B4: SKU2 | C4: 11.319683 | D4: 34 | E4: 8 | F4: 9577.7496 | G4: Unknown | H4: 1 | I4: 10 | J4: 88 | K4: 2 | L4: 480 | M4: Carrier B | N4: Supplier 1 | O4: Mumbai | P4: 971 | Q4: 27 | R4: 30.688019 | S4: Pending | T4: 4.5805926 | U4: Air | V4: Route C | W4: 141.92028
A5: skincare | B5: SKU3 | C5: 61.163343 | D5: 68 | E5: 83 | F5: 7766.8364 | G5: Non-binary | H5: 23 | I5: 13 | J5: 59 | K5: 6 | L5: 945 | M5: Carrier C | N5: Supplier 5 | O5: Kolkata | P5: 937 | Q5: 18 | R5: 35.624741 | S5: Fail | T5: 4.7466486 | U5: Rail | V5: Route A | W5: 254.77616
A6: skincare | B6: SKU4 | C6: 4.805496 | D6: 26 | E6: 871 | F6: 2686.5052 | G6: Non-binary | H6: 5 | I6: 3 | J6: 56 | K6: 8 | L6: 932 | M6: Carrier A | N6: Supplier 1 | O6: Delhi | P6: 414 | Q6: 3 | R6: 92.065161 | S6: Fail | T6: 3.1455795 | U6: Air | V6: Route A | W6: 923.44063
A7: haircare | B7: SKU5 | C7: 1.699976 | D7: 87 | E7: 147 | F7: 2828.3487 | G7: Non-binary | H7: 90 | I7: 27 | J7: 66 | K7: 3 | L7: 466 | M7: Carrier B | N7: Supplier 4 | O7: Bangalore | P7: 104 | Q7: 17 | R7: 56.766476 | S7: Fail | T7: 2.7791935 | U7: Road | V7: Route A | W7: 235.46124
A8: skincare | B8: SKU6 | C8: 4.0783329 | D8: 48 | E8: 65 | F8: 7823.4766 | G8: Male | H8: 11 | I8: 15 | J8: 58 | K8: 8 | L8: 759 | M8: Carrier C | N8: Supplier 3 | O8: Kolkata | P8: 314 | Q8: 24 | R8: 1.0850686 | S8: Pending | T8: 1.0009106 | U8: Sea | V8: Route A | W8: 134.3691
A9: cosmetics | B9: SKU7 | C9: 42.958384 | D9: 59 | E9: 426 | F9: 8496.1038 | G9: Female | H9: 93 | I9: 17 | J9: 11 | K9: 1 | L9: 388 | M9: Carrier B | N9: Supplier 4 | O9: Bangalore | P9: 564 | Q9: 1 | R9: 99.466109 | S9: Fail | T9: 0.39817719 | U9: Road | V9: Route C | W9: 802.05631
A10: cosmetics | B10: SKU8 | C10: 68.717597 | D10: 78 | E10: 150 | F10: 7517.3632 | G10: Female | H10: 5 | I10: 10 | J10: 15 | K10: 7 | L10: 388 | M10: Carrier C | N10: Supplier 4 | O10: Mumbai | P10: 769 | Q10: 8 | R10: 11.423027 | S10: Pending | T10: 2.7098627 | U10: Sea | V10: Route B | W10: 505.55713
A11: skincare | B11: SKU9 | C11: 64.015733 | D11: 35 | E11: 980 | F11: 4971.146 | G11: Unknown | H11: 14 | I11: 27 | J11: 83 | K11: 1 | L11: 1098 | M11: Carrier A | N11: Supplier 2 | O11: Chennai | P11: 963 | Q11: 23 | R11: 47.957602 | S11: Pending | T11: 3.8446145 | U11: Rail | V11: Route B | W11: 995.92946
A12: skincare | B12: SKU10 | C12: 15.707796 | D12: 11 | E12: 996 | F12: 2330.9658 | G12: Non-binary | H12: 51 | I12: 13 | J12: 80 | K12: 2 | L12: 1074 | M12: Carrier C | N12: Supplier 5 | O12: Kolkata | P12: 830 | Q12: 5 | R12: 96.527353 | S12: Pass | T12: 1.7273139 | U12: Road | V12: Route B | W12: 806.10318
A13: skincare | B13: SKU11 | C13: 90.63546 | D13: 95 | E13: 960 | F13: 6099.9441 | G13: Female | H13: 46 | I13: 23 | J13: 60 | K13: 1 | L13: 972 | M13: Carrier A | N13: Supplier 2 | O13: Kolkata | P13: 362 | Q13: 11 | R13: 27.592363 | S13: Pending | T13: 0.021169821 | U13: Air | V13: Route A | W13: 126.72303
... A100: skincare | B100: SKU98 | C100: 19.754605 | D100: 43 | E100: 913 | F100: 8525.9526 | G100: Female | H100: 53 | I100: 1 | J100: 27 | K100: 7 | L100: 1109 | M100: Carrier B | N100: Supplier 5 | O100: Chennai | P100: 581 | Q100: 9 | R100: 5.6046909 | S100: Pending | T100: 2.9081222 | U100: Rail | V100: Route A | W100: 882.19886
A101: haircare | B101: SKU99 | C101: 68.517833 | D101: 17 | E101: 627 | F101: 9185.1858 | G101: Unknown | H101: 55 | I101: 8 | J101: 59 | K101: 6 | M101: Carrier B | N101: Supplier 2 | O101: Chennai | P101: 921 | Q101: 2 | R101: 38.072899 | S101: Fail | T101: 0.34602729 | U101: Rail | V101: Route B | W101: 210.74301

Sheet Clean_Data
A1: Product type | B1: SKU | C1: Price | D1: Availability | E1: Number of products sold | F1: Revenue generated | G1: Customer demographics | H1: Stock levels | I1: Supplier Lead time | J1: Order quantities | K1: Shipping times | L1: Shipping carriers | M1: Shipping costs | N1: Supplier name | O1: Location | P1: Production volumes | Q1: Manufacturing lead time | R1: Manufacturing costs | S1: Inspection results | T1: Defect rates | U1: Transportation modes | V1: Routes | W1: Costs | X1: Total Costs | Y1: Estimated Profit | Z1: Inventory Efficiency | AA1: Revenue Per Unit | AB1: ShIpping cost per unit | AC1: Total Lead Time
A2: haircare | B2: SKU0 | C2: 69.808006 | D2: 55 | E2: 802 | F2: 8661.9968 | G2: Non-binary | H2: 58 | I2: 7 | J2: 96 | K2: 4 | L2: Carrier B | M2: 103 | N2: Supplier 3 | O2: Mumbai | P2: 215 | Q2: 29 | R2: 46.279879 | S2: Pending | T2: 0.22641036 | U2: Road | V2: Route B | W2: 187.75208 | X2: =SupplyChain4[[#This Row],[Costs]]+SupplyChain4[[#This Row],[Shipping costs]]+SupplyChain4[[#This Row],[Manufacturing costs]] -> 337.03195 | Y2: =SupplyChain4[[#This Row],[Revenue generated]]-SupplyChain4[[#This Row],[Total Costs]] -> 8324.9648 | Z2: =IF(SupplyChain4[[#This Row],[Stock levels]]=0,"",SupplyChain4[[#This Row],[Number of products sold]]/SupplyChain4[[#This Row],[Stock levels]]) -> 13.827586 | AA2: =IFERROR(SupplyChain4[[#This Row],[Revenue generated]]/SupplyChain4[[#This Row],[Number of products sold]],0) -> 10.800495 | AB2: =IFERROR(SupplyChain4[[#This Row],[Shipping costs]]/SupplyChain4[[#This Row],[Number of products sold]],0) -> 0.12842893 | AC2: =SupplyChain4[[#This Row],[Supplier Lead time]]+SupplyChain4[[#This Row],[Shipping times]]+SupplyChain4[[#This Row],[Manufacturing lead time]] -> 40
A3: skincare | B3: SKU1 | C3: 14.843523 | D3: 95 | E3: 736 | F3: 7460.9001 | G3: Female | H3: 53 | I3: 30 | J3: 37 | K3: 2 | L3: Carrier A | M3: 938 | N3: Supplier 3 | O3: Mumbai | P3: 517 | Q3: 30 | R3: 33.616769 | S3: Pending | T3: 4.854068 | U3: Road | V3: Route B | W3: 503.06558 | X3: =SupplyChain4[[#This Row],[Costs]]+SupplyChain4[[#This Row],[Shipping costs]]+SupplyChain4[[#This Row],[Manufacturing costs]] -> 1474.6823 | Y3: =SupplyChain4[[#This Row],[Revenue generated]]-SupplyChain4[[#This Row],[Total Costs]] -> 5986.2177 | Z3: =IF(SupplyChain4[[#This Row],[Stock levels]]=0,"",SupplyChain4[[#This Row],[Number of products sold]]/SupplyChain4[[#This Row],[Stock levels]]) -> 13.886792 | AA3: =IFERROR(SupplyChain4[[#This Row],[Revenue generated]]/SupplyChain4[[#This Row],[Number of products sold]],0) -> 10.137092 | AB3: =IFERROR(SupplyChain4[[#This Row],[Shipping costs]]/SupplyChain4[[#This Row],[Number of products sold]],0) -> 1.2744565 | AC3: =SupplyChain4[[#This Row],[Supplier Lead time]]+SupplyChain4[[#This Row],[Shipping times]]+SupplyChain4[[#This Row],[Manufacturing lead time]] -> 62
A4: haircare | B4: SKU2 | C4: 11.319683 | D4: 34 | E4: 635 | F4: 9577.7496 | G4: Unknown | H4: 24 | I4: 10 | J4: 88 | K4: 2 | L4: Carrier B | M4: 480 | N4: Supplier 1 | O4: Mumbai | P4: 971 | Q4: 27 | R4: 30.688019 | S4: Pending | T4: 4.5805926 | U4: Air | V4: Route C | W4: 141.92028 | X4: =SupplyChain4[[#This Row],[Costs]]+SupplyChain4[[#This Row],[Shipping costs]]+SupplyChain4[[#This Row],[Manufacturing costs]] -> 652.6083 | Y4: =SupplyChain4[[#This Row],[Revenue generated]]-SupplyChain4[[#This Row],[Total Costs]] -> 8925.1413 | Z4: =IF(SupplyChain4[[#This Row],[Stock levels]]=0,"",SupplyChain4[[#This Row],[Number of products sold]]/SupplyChain4[[#This Row],[Stock levels]]) -> 26.458333 | AA4: =IFERROR(SupplyChain4[[#This Row],[Revenue generated]]/SupplyChain4[[#This Row],[Number of products sold]],0) -> 15.08307 | AB4: =IFERROR(SupplyChain4[[#This Row],[Shipping costs]]/SupplyChain4[[#This Row],[Number of products sold]],0) -> 0.75590551 | AC4: =SupplyChain4[[#This Row],[Supplier Lead time]]+SupplyChain4[[#This Row],[Shipping times]]+SupplyChain4[[#This Row],[Manufacturing lead time]] -> 39
A5: skincare | B5: SKU3 | C5: 61.163343 | D5: 68 | E5: 83 | F5: 7766.8364 | G5: Non-binary | H5: 23 | I5: 13 | J5: 59 | K5: 6 | L5: Carrier C | M5: 945 | N5: Supplier 5 | O5: Kolkata | P5: 937 | Q5: 18 | R5: 35.624741 | S5: Fail | T5: 4.7466486 | U5: Rail | V5: Route A | W5: 254.77616 | X5: =SupplyChain4[[#This Row],[Costs]]+SupplyChain4[[#This Row],[Shipping costs]]+SupplyChain4[[#This Row],[Manufacturing costs]] -> 1235.4009 | Y5: =SupplyChain4[[#This Row],[Revenue generated]]-SupplyChain4[[#This Row],[Total Costs]] -> 6531.4355 | Z5: =IF(SupplyChain4[[#This Row],[Stock levels]]=0,"",SupplyChain4[[#This Row],[Number of products sold]]/SupplyChain4[[#This Row],[Stock levels]]) -> 3.6086957 | AA5: =IFERROR(SupplyChain4[[#This Row],[Revenue generated]]/SupplyChain4[[#This Row],[Number of products sold]],0) -> 93.576342 | AB5: =IFERROR(SupplyChain4[[#This Row],[Shipping costs]]/SupplyChain4[[#This Row],[Number of products sold]],0) -> 11.385542 | AC5: =SupplyChain4[[#This Row],[Supplier Lead time]]+SupplyChain4[[#This Row],[Shipping times]]+SupplyChain4[[#This Row],[Manufacturing lead time]] -> 37
A6: skincare | B6: SKU4 | C6: 4.805496 | D6: 26 | E6: 871 | F6: 2686.5052 | G6: Non-binary | H6: 5 | I6: 3 | J6: 56 | K6: 8 | L6: Carrier A | M6: 932 | N6: Supplier 1 | O6: Delhi | P6: 414 | Q6: 3 | R6: 92.065161 | S6: Fail | T6: 3.1455795 | U6: Air | V6: Route A | W6: 923.44063 | X6: =SupplyChain4[[#This Row],[Costs]]+SupplyChain4[[#This Row],[Shipping costs]]+SupplyChain4[[#This Row],[Manufacturing costs]] -> 1947.5058 | Y6: =SupplyChain4[[#This Row],[Revenue generated]]-SupplyChain4[[#This Row],[Total Costs]] -> 738.99936 | Z6: =IF(SupplyChain4[[#This Row],[Stock levels]]=0,"",SupplyChain4[[#This Row],[Number of products sold]]/SupplyChain4[[#This Row],[Stock levels]]) -> 174.2 | AA6: =IFERROR(SupplyChain4[[#This Row],[Revenue generated]]/SupplyChain4[[#This Row],[Number of products sold]],0) -> 3.0843917 | AB6: =IFERROR(SupplyChain4[[#This Row],[Shipping costs]]/SupplyChain4[[#This Row],[Number of products sold]],0) -> 1.0700344 | AC6: =SupplyChain4[[#This Row],[Supplier Lead time]]+SupplyChain4[[#This Row],[Shipping times]]+SupplyChain4[[#This Row],[Manufacturing lead time]] -> 14
A7: haircare | B7: SKU5 | C7: 1.699976 | D7: 87 | E7: 147 | F7: 2828.3487 | G7: Non-binary | H7: 90 | I7: 27 | J7: 66 | K7: 3 | L7: Carrier B | M7: 466 | N7: Supplier 4 | O7: Bangalore | P7: 104 | Q7: 17 | R7: 56.766476 | S7: Fail | T7: 2.7791935 | U7: Road | V7: Route A | W7: 235.46124 | X7: =SupplyChain4[[#This Row],[Costs]]+SupplyChain4[[#This Row],[Shipping costs]]+SupplyChain4[[#This Row],[Manufacturing costs]] -> 758.22771 | Y7: =SupplyChain4[[#This Row],[Revenue generated]]-SupplyChain4[[#This Row],[Total Costs]] -> 2070.121 | Z7: =IF(SupplyChain4[[#This Row],[Stock levels]]=0,"",SupplyChain4[[#This Row],[Number of products sold]]/SupplyChain4[[#This Row],[Stock levels]]) -> 1.6333333 | AA7: =IFERROR(SupplyChain4[[#This Row],[Revenue generated]]/SupplyChain4[[#This Row],[Number of products sold]],0) -> 19.240468 | AB7: =IFERROR(SupplyChain4[[#This Row],[Shipping costs]]/SupplyChain4[[#This Row],[Number of products sold]],0) -> 3.170068 | AC7: =SupplyChain4[[#This Row],[Supplier Lead time]]+SupplyChain4[[#This Row],[Shipping times]]+SupplyChain4[[#This Row],[Manufacturing lead time]] -> 47
A8: skincare | B8: SKU6 | C8: 4.0783329 | D8: 48 | E8: 65 | F8: 7823.4766 | G8: Male | H8: 11 | I8: 15 | J8: 58 | K8: 8 | L8: Carrier C | M8: 759 | N8: Supplier 3 | O8: Kolkata | P8: 314 | Q8: 24 | R8: 1.0850686 | S8: Pending | T8: 1.0009106 | U8: Sea | V8: Route A | W8: 134.3691 | X8: =SupplyChain4[[#This Row],[Costs]]+SupplyChain4[[#This Row],[Shipping costs]]+SupplyChain4[[#This Row],[Manufacturing costs]] -> 894.45417 | Y8: =SupplyChain4[[#This Row],[Revenue generated]]-SupplyChain4[[#This Row],[Total Costs]] -> 6929.0224 | Z8: =IF(SupplyChain4[[#This Row],[Stock levels]]=0,"",SupplyChain4[[#This Row],[Number of products sold]]/SupplyChain4[[#This Row],[Stock levels]]) -> 5.9090909 | AA8: =IFERROR(SupplyChain4[[#This Row],[Revenue generated]]/SupplyChain4[[#This Row],[Number of products sold]],0) -> 120.36118 | AB8: =IFERROR(SupplyChain4[[#This Row],[Shipping costs]]/SupplyChain4[[#This Row],[Number of products sold]],0) -> 11.676923 | AC8: =SupplyChain4[[#This Row],[Supplier Lead time]]+SupplyChain4[[#This Row],[Shipping times]]+SupplyChain4[[#This Row],[Manufacturing lead time]] -> 47
A9: cosmetics | B9: SKU7 | C9: 42.958384 | D9: 59 | E9: 426 | F9: 8496.1038 | G9: Female | H9: 93 | I9: 17 | J9: 11 | K9: 1 | L9: Carrier B | M9: 388 | N9: Supplier 4 | O9: Bangalore | P9: 564 | Q9: 1 | R9: 99.466109 | S9: Fail | T9: 0.39817719 | U9: Road | V9: Route C | W9: 802.05631 | X9: =SupplyChain4[[#This Row],[Costs]]+SupplyChain4[[#This Row],[Shipping costs]]+SupplyChain4[[#This Row],[Manufacturing costs]] -> 1289.5224 | Y9: =SupplyChain4[[#This Row],[Revenue generated]]-SupplyChain4[[#This Row],[Total Costs]] -> 7206.5814 | Z9: =IF(SupplyChain4[[#This Row],[Stock levels]]=0,"",SupplyChain4[[#This Row],[Number of products sold]]/SupplyChain4[[#This Row],[Stock levels]]) -> 4.5806452 | AA9: =IFERROR(SupplyChain4[[#This Row],[Revenue generated]]/SupplyChain4[[#This Row],[Number of products sold]],0) -> 19.943906 | AB9: =IFERROR(SupplyChain4[[#This Row],[Shipping costs]]/SupplyChain4[[#This Row],[Number of products sold]],0) -> 0.91079812 | AC9: =SupplyChain4[[#This Row],[Supplier Lead time]]+SupplyChain4[[#This Row],[Shipping times]]+SupplyChain4[[#This Row],[Manufacturing lead time]] -> 19
A10: cosmetics | B10: SKU8 | C10: 68.717597 | D10: 78 | E10: 150 | F10: 7517.3632 | G10: Female | H10: 5 | I10: 10 | J10: 15 | K10: 7 | L10: Carrier C | M10: 388 | N10: Supplier 4 | O10: Mumbai | P10: 769 | Q10: 8 | R10: 11.423027 | S10: Pending | T10: 2.7098627 | U10: Sea | V10: Route B | W10: 505.55713 | X10: =SupplyChain4[[#This Row],[Costs]]+SupplyChain4[[#This Row],[Shipping costs]]+SupplyChain4[[#This Row],[Manufacturing costs]] -> 904.98016 | Y10: =SupplyChain4[[#This Row],[Revenue generated]]-SupplyChain4[[#This Row],[Total Costs]] -> 6612.383 | Z10: =IF(SupplyChain4[[#This Row],[Stock levels]]=0,"",SupplyChain4[[#This Row],[Number of products sold]]/SupplyChain4[[#This Row],[Stock levels]]) -> 30 | AA10: =IFERROR(SupplyChain4[[#This Row],[Revenue generated]]/SupplyChain4[[#This Row],[Number of products sold]],0) -> 50.115755 | AB10: =IFERROR(SupplyChain4[[#This Row],[Shipping costs]]/SupplyChain4[[#This Row],[Number of products sold]],0) -> 2.5866667 | AC10: =SupplyChain4[[#This Row],[Supplier Lead time]]+SupplyChain4[[#This Row],[Shipping times]]+SupplyChain4[[#This Row],[Manufacturing lead time]] -> 25
A11: skincare | B11: SKU9 | C11: 64.015733 | D11: 35 | E11: 980 | F11: 4971.146 | G11: Unknown | H11: 14 | I11: 27 | J11: 83 | K11: 1 | L11: Carrier A | M11: 1098 | N11: Supplier 2 | O11: Chennai | P11: 963 | Q11: 23 | R11: 47.957602 | S11: Pending | T11: 3.8446145 | U11: Rail | V11: Route B | W11: 995.92946 | X11: =SupplyChain4[[#This Row],[Costs]]+SupplyChain4[[#This Row],[Shipping costs]]+SupplyChain4[[#This Row],[Manufacturing costs]] -> 2141.8871 | Y11: =SupplyChain4[[#This Row],[Revenue generated]]-SupplyChain4[[#This Row],[Total Costs]] -> 2829.2589 | Z11: =IF(SupplyChain4[[#This Row],[Stock levels]]=0,"",SupplyChain4[[#This Row],[Number of products sold]]/SupplyChain4[[#This Row],[Stock levels]]) -> 70 | AA11: =IFERROR(SupplyChain4[[#This Row],[Revenue generated]]/SupplyChain4[[#This Row],[Number of products sold]],0) -> 5.0725979 | AB11: =IFERROR(SupplyChain4[[#This Row],[Shipping costs]]/SupplyChain4[[#This Row],[Number of products sold]],0) -> 1.1204082 | AC11: =SupplyChain4[[#This Row],[Supplier Lead time]]+SupplyChain4[[#This Row],[Shipping times]]+SupplyChain4[[#This Row],[Manufacturing lead time]] -> 51
A12: skincare | B12: SKU10 | C12: 15.707796 | D12: 11 | E12: 996 | F12: 2330.9658 | G12: Non-binary | H12: 51 | I12: 13 | J12: 80 | K12: 2 | L12: Carrier C | M12: 1074 | N12: Supplier 5 | O12: Kolkata | P12: 830 | Q12: 5 | R12: 96.527353 | S12: Pass | T12: 1.7273139 | U12: Road | V12: Route B | W12: 806.10318 | X12: =SupplyChain4[[#This Row],[Costs]]+SupplyChain4[[#This Row],[Shipping costs]]+SupplyChain4[[#This Row],[Manufacturing costs]] -> 1976.6305 | Y12: =SupplyChain4[[#This Row],[Revenue generated]]-SupplyChain4[[#This Row],[Total Costs]] -> 354.33527 | Z12: =IF(SupplyChain4[[#This Row],[Stock levels]]=0,"",SupplyChain4[[#This Row],[Number of products sold]]/SupplyChain4[[#This Row],[Stock levels]]) -> 19.529412 | AA12: =IFERROR(SupplyChain4[[#This Row],[Revenue generated]]/SupplyChain4[[#This Row],[Number of products sold]],0) -> 2.3403271 | AB12: =IFERROR(SupplyChain4[[#This Row],[Shipping costs]]/SupplyChain4[[#This Row],[Number of products sold]],0) -> 1.0783133 | AC12: =SupplyChain4[[#This Row],[Supplier Lead time]]+SupplyChain4[[#This Row],[Shipping times]]+SupplyChain4[[#This Row],[Manufacturing lead time]] -> 20
A13: skincare | B13: SKU11 | C13: 90.63546 | D13: 95 | E13: 960 | F13: 6099.9441 | G13: Female | H13: 46 | I13: 23 | J13: 60 | K13: 1 | L13: Carrier A | M13: 972 | N13: Supplier 2 | O13: Kolkata | P13: 362 | Q13: 11 | R13: 27.592363 | S13: Pending | T13: 0.021169821 | U13: Air | V13: Route A | W13: 126.72303 | X13: =SupplyChain4[[#This Row],[Costs]]+SupplyChain4[[#This Row],[Shipping costs]]+SupplyChain4[[#This Row],[Manufacturing costs]] -> 1126.3154 | Y13: =SupplyChain4[[#This Row],[Revenue generated]]-SupplyChain4[[#This Row],[Total Costs]] -> 4973.6287 | Z13: =IF(SupplyChain4[[#This Row],[Stock levels]]=0,"",SupplyChain4[[#This Row],[Number of products sold]]/SupplyChain4[[#This Row],[Stock levels]]) -> 20.869565 | AA13: =IFERROR(SupplyChain4[[#This Row],[Revenue generated]]/SupplyChain4[[#This Row],[Number of products sold]],0) -> 6.3541085 | AB13: =IFERROR(SupplyChain4[[#This Row],[Shipping costs]]/SupplyChain4[[#This Row],[Number of products sold]],0) -> 1.0125 | AC13: =SupplyChain4[[#This Row],[Supplier Lead time]]+SupplyChain4[[#This Row],[Shipping times]]+SupplyChain4[[#This Row],[Manufacturing lead time]] -> 35
... A101: haircare | B101: SKU99 | C101: 68.517833 | D101: 17 | E101: 627 | F101: 9185.1858 | G101: Unknown | H101: 55 | I101: 8 | J101: 59 | K101: 6 | L101: Carrier B | M101: 228 | N101: Supplier 2 | O101: Chennai | P101: 921 | Q101: 2 | R101: 38.072899 | S101: Fail | T101: 0.34602729 | U101: Rail | V101: Route B | W101: 210.74301 | X101: =SupplyChain4[[#This Row],[Costs]]+SupplyChain4[[#This Row],[Shipping costs]]+SupplyChain4[[#This Row],[Manufacturing costs]] -> 476.81591 | Y101: =SupplyChain4[[#This Row],[Revenue generated]]-SupplyChain4[[#This Row],[Total Costs]] -> 8708.3699 | Z101: =IF(SupplyChain4[[#This Row],[Stock levels]]=0,"",SupplyChain4[[#This Row],[Number of products sold]]/SupplyChain4[[#This Row],[Stock levels]]) -> 11.4 | AA101: =IFERROR(SupplyChain4[[#This Row],[Revenue generated]]/SupplyChain4[[#This Row],[Number of products sold]],0) -> 14.649419 | AB101: =IFERROR(SupplyChain4[[#This Row],[Shipping costs]]/SupplyChain4[[#This Row],[Number of products sold]],0) -> 0.36363636 | AC101: =SupplyChain4[[#This Row],[Supplier Lead time]]+SupplyChain4[[#This Row],[Shipping times]]+SupplyChain4[[#This Row],[Manufacturing lead time]] -> 16

Sheet KPIs
A1: Category | B1: KPI | C1: VALUE
A2: Sales | B2: Total Revenue | C2: =SUM(Clean_Data!F:F) -> 577604.82
A3: Sales | B3: Total Units Sold | C3: =SUM(Clean_Data!E:E) -> 46726
A4: Sales | B4: Average Price | C4: =AVERAGE(Clean_Data!C:C) -> 49.462461
A5: Sales | B5: Average Revenue Per Unit | C5: =AVERAGE(SupplyChain4[Revenue Per Unit]) -> 29.534957
A7: Inventory | B7: Average Stock Level | C7: =AVERAGE(Clean_Data!H:H) -> 48.23
A8: Inventory | B8: Total Stock | C8: =SUM(Clean_Data!H:H) -> 4823
A9: Inventory | B9: Average Availability | C9: =AVERAGE(Clean_Data!D:D) -> 48.4
A10: Inventory | B10: Average Inventory Efficiency | C10: =SUM(Clean_Data!E:E)/SUM(Clean_Data!H:H) -> 9.6881609
A12: Profitability | B12: Total Manufacturing Cost | C12: =SUM(Clean_Data!R:R) -> 4726.6693
A13: Profitability | B13: Total Shipping Cost | C13: =SUM(Clean_Data!M:M) -> 63905
A14: Profitability | B14: Total Transportation Cost | C14: =SUM(Clean_Data!X:X) -> 121556.25
A15: Profitability | B15: Estimated Total Cost | C15: =SUM(Clean_Data!X:X) -> 121556.25
A16: Profitability | B16: Estimated Total Profit | C16: =SUM(Clean_Data!Y:Y) -> 456048.57
A17: Profitability | B17: Average Profit | C17: =AVERAGE(Clean_Data!Y:Y) -> 4560.4857
A18: Profitability | B18: Profit Margin | C18: =SUM(Clean_Data!Y:Y)/SUM(Clean_Data!F:F) -> 0.78955119
A20: Supplier | B20: Number of Suppliers | C20: =COUNTA(_xlfn.UNIQUE(Clean_Data!N:N)) -> 7
A21: Supplier | B21: Average Supplier Lead Time | C21: =AVERAGE(Clean_Data!I:I) -> 15.96
A22: Supplier | B22: Average Manufacturing Cost | C22: =AVERAGE(Clean_Data!R:R) -> 47.266693
A24: Quality | B24: Average Defect Rate | C24: =AVERAGE(SupplyChain4[Defect rates])% -> 0.02277158
A25: Quality | B25: Failed Inspections | C25: =COUNTIF(Clean_Data!S:S,"Fail") -> 36
A26: Quality | B26: Inspection Pass Rate | C26: =COUNTIF(Clean_Data!S:S,"Pass")/COUNTA(Clean_Data!S:S) -> 0.22772277
A28: Logistics | B28: Average Shipping Time | C28: =AVERAGE(Clean_Data!K:K) -> 5.75
A29: Logistics | B29: Total Shipping Cost | C29: =SUM(Clean_Data!M:M) -> 63905
A30: Logistics | B30: Average Shipping Cost | C30: =AVERAGE(Clean_Data!M:M) -> 639.05
A31: Logistics | B31: Average Shipping Cost per Unit | C31: =AVERAGE(SupplyChain4[ShIpping cost per unit]) -> 2.9375889
A32: Logistics | B32: Average Lead Time | C32: =AVERAGE(Clean_Data!AC:AC) -> 36.48

Sheet Pivot_Analysis
A1: REVENUE BY PRODUCT TYPE | F1: SUPPLIER PERFORMANCE
A2: Product type | B2: Total Revenue | C2: Total Units Sold | F2: Row Labels | G2: Avg Supplier Lead time | H2: Avg Defect Rates (%) | I2: Avg Manufacturing Costs | J2: Total Production Volumes
A3: skincare | B3: 241628.16 | C3: 20731 | F3: Supplier 1 | G3: 16.777778 | H3: 1.8036297 | I3: 45.254027 | J3: 13545
A4: haircare | B4: 174455.39 | C4: 14238 | F4: Supplier 2 | G4: 16.227273 | H4: 2.3627501 | I4: 41.622514 | J4: 14105
A5: cosmetics | B5: 161521.27 | C5: 11757 | F5: Supplier 3 | G5: 14.333333 | H5: 2.465786 | I5: 43.634121 | J5: 7997
A6: Grand Total | B6: 577604.82 | C6: 46726 | F6: Supplier 4 | G6: 17 | H6: 2.3373974 | I6: 62.709727 | J6: 11756
F7: Supplier 5 | G7: 14.722222 | H7: 2.6654083 | I7: 44.768243 | J7: 9381
F8: Grand Total | G8: 15.96 | H8: 2.277158 | I8: 47.266693 | J8: 56784
A10: TRANSPORTATION ANALYSIS | F10: ROUTE ANALYSIS
A11: Row Labels | B11: Avg Shipping Times | C11: Avg Shipping Costs | D11: Total Shipping Costs | F11: Row Labels | G11: Avg Shipping Costs | H11: Avg Shipping Times | I11: Total Revenue
A12: Air | B12: 5.1153846 | C12: 734.53846 | D12: 19098 | F12: Route A | G12: 648.34884 | H12: 6.0232558 | I12: 253198.85
A13: Rail | B13: 6.5714286 | C13: 590.96429 | D13: 16547 | F13: Route B | G13: 632.40541 | H13: 5.7027027 | I13: 204484.01
A14: Road | B14: 4.7241379 | C14: 585.68966 | D14: 16985 | F14: Route C | G14: 631.35 | H14: 5.25 | I14: 119921.96
A15: Sea | B15: 7.1176471 | C15: 663.23529 | D15: 11275 | F15: Grand Total | G15: 639.05 | H15: 5.75 | I15: 577604.82
A16: Grand Total | B16: 5.75 | C16: 639.05 | D16: 63905
A19: QUALITY ANALYSIS
A20: Row Labels | B20: Avg Defect Rate (%)
A21: cosmetics | B21: 1.919287
A22: haircare | B22: 2.4831502
A23: skincare | B23: 2.3346808
A24: Grand Total | B24: 2.277158

Sheet Chart
A1: Product type | B1: Total Revenue
A2: skincare | B2: 241628.16
A3: haircare | B3: 174455.39
A4: cosmetics | B4: 161521.27
A6: Row Labels | B6: Total Revenue | C6: Total Estimated Profit
A7: cosmetics | B7: 161521.27 | C7: 132560.5
A8: haircare | B8: 174455.39 | C8: 136463.96
A9: skincare | B9: 241628.16 | C9: 187024.12
A10: Grand Total | B10: 577604.82 | C10: 456048.57
A12: Supplier Name | B12: Average Defect Rate
A13: Supplier 1 | B13: 1.8036297
A14: Supplier 4 | B14: 2.3373974
A15: Supplier 2 | B15: 2.3627501
A16: Supplier 3 | B16: 2.465786
A17: Supplier 5 | B17: 2.6654083
A20: Row Labels | B20: Total Shipping Costs
A21: Air | B21: 19098
A22: Road | B22: 16985
A23: Rail | B23: 16547
A24: Sea | B24: 11275
A26: Row Labels | B26: Avg Shipping Times
A27: Sea | B27: 7.1176471
A28: Rail | B28: 6.5714286
A29: Air | B29: 5.1153846
A30: Road | B30: 4.7241379
A32: Total Lead Time | B32: Defect rates
A33: 40 | B33: 0.22641036
A34: 62 | B34: 4.854068
A35: 39 | B35: 4.5805926
A36: 37 | B36: 4.7466486
A37: 14 | B37: 3.1455795
A38: 47 | B38: 2.7791935
A39: 47 | B39: 1.0009106
A40: 19 | B40: 0.39817719
A41: 25 | B41: 2.7098627
A42: 51 | B42: 3.8446145
A43: 20 | B43: 1.7273139
A44: 35 | B44: 0.021169821
... A132: 16 | B132: 0.34602729

Sheet Deeper_analysis
A1: Row Labels | B1: Total Revenue generated | C1: Total Estimated Profit | D1: Avg Defect rates (%) | H1: CORRELATION
A2: skincare | B2: 241628.16 | C2: 187024.12 | D2: 2.3346808 | G2: Price vs Number of products sold | H2: =CORREL(A15:A114,B15:B114) -> 0.0057394844 | I2: There is little or no linear relationship between price and units sold
A3: haircare | B3: 174455.39 | C3: 136463.96 | D3: 2.4831502 | G3: Shipping times vs shipping costs | H3: =CORREL(F15:F114,G15:G114) -> -0.06290141 | I3: There is a negative correlation between shipping times and shipping costs
A4: cosmetics | B4: 161521.27 | C4: 132560.5 | D4: 1.919287 | G4: Manufacturing lead times vs Defect rates | H4: =CORREL(J15:J114,K15:K114) -> 0.13951848 | I4: There is little to no correlation between manufacturing lead time and defect rates
A5: Grand Total | B5: 577604.82 | C5: 456048.57 | D5: 2.277158
A7: Row Labels | B7: No. of products sold | C7: Total Stock levels | D7: Inventory Efficiency
A8: cosmetics | B8: 11757 | C8: 1525 | D8: =GETPIVOTDATA("No. of products sold",$A$7,"Product type","cosmetics")/GETPIVOTDATA("Total Stock levels",$A$7,"Product type","cosmetics") -> 7.7095082
A9: haircare | B9: 14238 | C9: 1667 | D9: =GETPIVOTDATA("No. of products sold",$A$7,"Product type","haircare")/GETPIVOTDATA("Total Stock levels",$A$7,"Product type","haircare") -> 8.5410918
A10: skincare | B10: 20731 | C10: 1631 | D10: =GETPIVOTDATA("No. of products sold",$A$7,"Product type","skincare")/GETPIVOTDATA("Total Stock levels",$A$7,"Product type","skincare") -> 12.710607
A11: Grand Total | B11: 46726 | C11: 4823 | D11: =GETPIVOTDATA("No. of products sold",$A$7)/GETPIVOTDATA("Total Stock levels",$A$7) -> 9.6881609
A14: Price | B14: Number of products sold | F14: Shipping times | G14: Shipping costs | J14: Manufacturing lead time | K14: Defect rates
A15: 69.808006 | B15: 802 | F15: 4 | G15: 103 | J15: 29 | K15: 0.22641036
A16: 14.843523 | B16: 736 | F16: 2 | G16: 938 | J16: 30 | K16: 4.854068
A17: 11.319683 | B17: 8 | F17: 2 | G17: 480 | J17: 27 | K17: 4.5805926
A18: 61.163343 | B18: 83 | F18: 6 | G18: 945 | J18: 18 | K18: 4.7466486
A19: 4.805496 | B19: 871 | F19: 8 | G19: 932 | J19: 3 | K19: 3.1455795
A20: 1.699976 | B20: 147 | F20: 3 | G20: 466 | J20: 17 | K20: 2.7791935
A21: 4.0783329 | B21: 65 | F21: 8 | G21: 759 | J21: 24 | K21: 1.0009106
A22: 42.958384 | B22: 426 | F22: 1 | G22: 388 | J22: 1 | K22: 0.39817719
A23: 68.717597 | B23: 150 | F23: 7 | G23: 388 | J23: 8 | K23: 2.7098627
A24: 64.015733 | B24: 980 | F24: 1 | G24: 1098 | J24: 23 | K24: 3.8446145
A25: 15.707796 | B25: 996 | F25: 2 | G25: 1074 | J25: 5 | K25: 1.7273139
A26: 90.63546 | B26: 960 | F26: 1 | G26: 972 | J26: 11 | K26: 0.021169821
... A114: 68.517833 | B114: 627 | F114: 6 | G114: 228 | J114: 2 | K114: 0.34602729

Sheet Dashboard
A1: SUPPLY CHAIN PERFORMANCE DASHBOARD
A4: TOTAL REVENUE | D4: TOTAL UNITS SOLD | G4: ESTIMATED PROFIT | J4: PROFIT MARGIN
A6: =KPIs!C2 -> 577604.82 | D6: =KPIs!C3 -> 46726 | G6: =KPIs!C16 -> 456048.57 | J6: =KPIs!C18 -> 0.78955119
